findabuse/__init__.py
findabuse/abuse.py
findabuse/cli.py
findabuse/dns.py
findabuse/http.py
findabuse/providers.py
findabuse/socket.py
findabuse/util.py
findabuse-0.1.14.dist-info/entry_points.txt
findabuse-0.1.14.dist-info/LICENSE
findabuse-0.1.14.dist-info/WHEEL
findabuse-0.1.14.dist-info/METADATA
findabuse-0.1.14.dist-info/RECORD
